IntLCA/__init__.py
IntLCA/intLCA.py
IntLCA_dev-0.1.0.dist-info/LICENSE
IntLCA_dev-0.1.0.dist-info/METADATA
IntLCA_dev-0.1.0.dist-info/WHEEL
IntLCA_dev-0.1.0.dist-info/top_level.txt
IntLCA_dev-0.1.0.dist-info/RECORD
