Metadata-Version: 2.1
Name: IntLCA-dev
Version: 0.1.0
Summary: IntLCA package for integrating emerging technologies in inventory matrices and performing large scale scenario analysis.
Home-page: https://github.com/MargotCha/Integrated_LCA/
Author: Margarita A. Charalambous
Author-email: ritabous2@gmail.com
Classifier: Programming Language :: Python :: 3
Classifier: License :: OSI Approved :: BSD License
Classifier: Operating System :: Microsoft :: Windows :: Windows 10
Requires-Python: >=3.8, <=3.12
License-File: LICENSE
Requires-Dist: brightway2 (==2.4.3)
Requires-Dist: premise (>=1.5.1)
Requires-Dist: ipython (==8.12.3)
Requires-Dist: jupyterlab
